Workbook

Sheet Assumptions
A1: FPA Executive Dashboard — DCF Valuation Model (5Y)
A2: Edit assumptions. The valuation summary updates automatically.
A4: Assumption | B4: Value | C4: Notes
A5: Revenue (Year 0) | B5: 2000000
A6: FCF Margin | B6: 0.12
A7: Revenue Growth (Y1–Y5) | B7: 0.1
A8: WACC / Discount Rate | B8: 0.11
A9: Terminal Growth Rate | B9: 0.03
A10: Net Debt (Debt - Cash) | B10: 250000
A11: Shares Outstanding | B11: 1000000

Sheet FCF Projection
A1: Free Cash Flow Projection
A3: Year | B3: Revenue | C3: FCF Margin | D3: FCF | E3: Discount Factor | F3: PV of FCF | G3: Notes
A4: 1 | B4: ='Assumptions'!B5*(1+'Assumptions'!B7) | C4: ='Assumptions'!B6 | D4: =B4*C4 | E4: =1/(1+'Assumptions'!B8)^1 | F4: =D4*E4
A5: 2 | B5: =B4*(1+'Assumptions'!B7) | C5: ='Assumptions'!B6 | D5: =B5*C5 | E5: =1/(1+'Assumptions'!B8)^2 | F5: =D5*E5
A6: 3 | B6: =B5*(1+'Assumptions'!B7) | C6: ='Assumptions'!B6 | D6: =B6*C6 | E6: =1/(1+'Assumptions'!B8)^3 | F6: =D6*E6
A7: 4 | B7: =B6*(1+'Assumptions'!B7) | C7: ='Assumptions'!B6 | D7: =B7*C7 | E7: =1/(1+'Assumptions'!B8)^4 | F7: =D7*E7
A8: 5 | B8: =B7*(1+'Assumptions'!B7) | C8: ='Assumptions'!B6 | D8: =B8*C8 | E8: =1/(1+'Assumptions'!B8)^5 | F8: =D8*E8
A9: TV | D9: =D8*(1+'Assumptions'!B9) | E9: =1/(1+'Assumptions'!B8)^5 | F9: =(D9/('Assumptions'!B8-'Assumptions'!B9))*E9 | G9: Terminal Value PV

Sheet Valuation Summary
A1: Valuation Summary
A3: PV of FCFs (Y1–Y5) | B3: =SUM('FCF Projection'!F4:F8)
A4: PV of Terminal Value | B4: ='FCF Projection'!F9
A5: Enterprise Value | B5: =B3+B4
A6: Less: Net Debt | B6: ='Assumptions'!B10
A7: Equity Value | B7: =B5-B6
A8: Shares Outstanding | B8: ='Assumptions'!B11
A9: Implied Value / Share | B9: =IF(B8=0,0,B7/B8)
A11: Scenario Toggle | B11: Base | C11: Use Bull/Bear by adjusting assumptions (growth, margin, WACC).

Sheet FA_Workstreams
A1: Financial Analyst Workstreams — 01 FPA Executive Dashboard
A2: This sheet summarizes how the Excel models + SQL + Python artifacts in this project map to core Financial Analyst responsibilities.
A4: Workstream | B4: What you do | C4: Key metrics | D4: Tools used | E4: Deliverables
A5: Budgeting & Forecasting | B5: Develop annual budgets and rolling forecasts using driver-based assumptions and scenario modeling. | C5: Revenue, Gross Margin, OpEx, EBITDA, Net Income, Cash Flow, Budget vs Actual (BvA) variances | D5: Excel (Budget vs Actual + Forecast + Scenario Toggle), Power BI/Tableau dashboards | E5: Annual budget workbook, 12-month rolling forecast, best/base/worst scenario summary
A6: Financial Analysis | B6: Analyze performance, identify trends, explain variances, and assess profitability at product/department level. | C6: MoM/QoQ/YoY growth, variance % and $ impact, contribution margin, ROA/ROIC, unit economics | D6: SQL (joins, KPI tables), Excel (variance bridge), Python (trend charts) | E6: Variance bridge, profitability by segment, trend commentary + recommendation bullets
A7: Strategic Planning | B7: Support long-term goals, capital allocation, and evaluate new investments/projects with ROI logic. | C7: NPV, IRR, Payback Period, CAC:LTV, portfolio mix, capacity/utilization | D7: Excel (DCF/NPV models), SQL (cohorts/segments), dashboards for exec review | E7: Investment memo inputs, capital allocation scenario, go/no-go recommendation
A8: Business Partnering | B8: Collaborate with Sales/Marketing/R&D/Ops to understand financial impacts and drive operational improvements. | C8: Pipeline-to-revenue, price/volume/mix, campaign ROI, churn/retention impact, cost-to-serve | D8: Stakeholder intake template, KPI scorecard, scenario toggle for tradeoffs | E8: Cross-functional KPI scorecard, action plan with owners/dates, impact estimate
A9: Reporting | B9: Create clear reports and presentations for senior management/board with consistent definitions and story. | C9: Executive KPIs, variance callouts, forecast accuracy, risk/opportunity pipeline | D9: PowerPoint-ready exports, dashboard screenshots, narrative summary in Excel | E9: Monthly performance pack, board-ready highlights, one-page exec summary
A11: How to use: Keep this tab in your GitHub Excel artifacts. When presenting your project, reference this sheet to explain how your models support budgeting, forecasting, strategic decisions, and executive reporting.

Sheet Executive_Reporting_Pack
A1: Executive Reporting Pack
A3: KPI Snapshot
A4: • Revenue Growth (YoY): 14.8%
A5: • Gross Margin: 62.4%
A6: • Operating Margin: 28.1%
A7: • Customer Acquisition Cost: $42
A8: • LTV:CAC Ratio: 5.6x
A10: Key Highlights
A11: • Strong revenue acceleration driven by enterprise customer expansion.
A12: • Marketing efficiency improved with CAC down 11% quarter-over-quarter.
A13: • High-margin product mix shift contributed to margin expansion.
A15: Risks & Watchouts
... A22: • Update pricing experiments for underperforming plans.
