Workbook

Sheet Assumptions
A1: FP&A Executive Model (2023-2025)
A3: Valuation Assumptions
A4: Metric | B4: Value | C4: Notes
A5: WACC | B5: 0.1 | C5: Discount rate used for valuation
A6: Terminal growth | B6: 0.03 | C6: Perpetual growth after forecast period
A7: Tax rate | B7: 0.24 | C7: Effective tax rate
A8: Depreciation % of Revenue | B8: 0.04 | C8: Proxy for D&A
A9: Capex % of Revenue | B9: 0.05 | C9: Capital expenditures
A10: NWC % of Revenue | B10: 0.02 | C10: Net working capital investment

Sheet P&L
A1: Income Statement (Monthly, Actual)
A2: Line Item | B2: 2025-01 | C2: 2025-02 | D2: 2025-03 | E2: 2025-04 | F2: 2025-05 | G2: 2025-06 | H2: 2025-07 | I2: 2025-08 | J2: 2025-09 | K2: 2025-10 | L2: 2025-11 | M2: 2025-12 | N2: FY Total
A3: Revenue | B3: 2000000 | C3: 2050000 | D3: 2100000 | E3: 2150000 | F3: 2200000 | G3: 2250000 | H3: 2300000 | I3: 2350000 | J3: 2400000 | K3: 2450000 | L3: 2500000 | M3: 2550000 | N3: =SUM(B3:M3)
A4: COGS | B4: =-0.62*B3 | C4: =-0.62*C3 | D4: =-0.62*D3 | E4: =-0.62*E3 | F4: =-0.62*F3 | G4: =-0.62*G3 | H4: =-0.62*H3 | I4: =-0.62*I3 | ... M4: =-0.62*M3 | N4: =SUM(B4:M4)
A5: Gross Profit | B5: =B3+B4 | C5: =C3+C4 | D5: =D3+D4 | E5: =E3+E4 | F5: =F3+F4 | G5: =G3+G4 | H5: =H3+H4 | I5: =I3+I4 | ... M5: =M3+M4 | N5: =SUM(B5:M5)
A6: Opex | B6: =-0.28*B3 | C6: =-0.28*C3 | D6: =-0.28*D3 | E6: =-0.28*E3 | F6: =-0.28*F3 | G6: =-0.28*G3 | H6: =-0.28*H3 | I6: =-0.28*I3 | ... M6: =-0.28*M3 | N6: =SUM(B6:M6)
A7: Operating Income | B7: =B5+B6 | C7: =C5+C6 | D7: =D5+D6 | E7: =E5+E6 | F7: =F5+F6 | G7: =G5+G6 | H7: =H5+H6 | I7: =I5+I6 | ... M7: =M5+M6 | N7: =SUM(B7:M7)

Sheet Budget_vs_Actual
A1: Budget vs Actual (FY2025)
A2: Metric | B2: Actual | C2: Budget | D2: Variance | E2: Variance % | F2: Commentary | G2: Owner | H2: Decision
A3: Revenue | B3: ='P&L'!N3 | C3: =B3*1.03 | D3: =B3-C3 | E3: =IF(C3=0,0,D3/C3) | G3: FP&A | H3: Monitor
A4: Gross Margin % | B4: =('P&L'!N5)/('P&L'!N3) | C4: =B4*1.02 | D4: =B4-C4 | E4: =IF(C4=0,0,D4/C4) | G4: FP&A | H4: Monitor
A5: Opex | B5: ='P&L'!N5 | C5: =B5*1.02 | D5: =B5-C5 | E5: =IF(C5=0,0,D5/C5) | G5: FP&A | H5: Reduce spend
A6: Operating Income | B6: ='P&L'!N6 | C6: =B6*1.03 | D6: =B6-C6 | E6: =IF(C6=0,0,D6/C6) | G6: FP&A | H6: Monitor

Sheet DCF_Valuation
A1: DCF Valuation (Illustrative)
A2: Year | B2: Revenue | C2: EBIT % | D2: EBIT | E2: Tax | F2: NOPAT | G2: FCF
A3: 2026 | B3: 30000000 | C3: 0.18 | D3: =B3*C3 | E3: =-Assumptions!B5*D3 | F3: =D3+E3 | G3: =F3 - (Assumptions!B7*B3) - (Assumptions!B6*B3) - (Assumptions!B8*B3)
A4: 2027 | B4: 32400000 | C4: 0.18 | D4: =B4*C4 | E4: =-Assumptions!B5*D4 | F4: =D4+E4 | G4: =F4 - (Assumptions!B7*B4) - (Assumptions!B6*B4) - (Assumptions!B8*B4)
A5: 2028 | B5: 34992000 | C5: 0.18 | D5: =B5*C5 | E5: =-Assumptions!B5*D5 | F5: =D5+E5 | G5: =F5 - (Assumptions!B7*B5) - (Assumptions!B6*B5) - (Assumptions!B8*B5)
A6: 2029 | B6: 37791360 | C6: 0.18 | D6: =B6*C6 | E6: =-Assumptions!B5*D6 | F6: =D6+E6 | G6: =F6 - (Assumptions!B7*B6) - (Assumptions!B6*B6) - (Assumptions!B8*B6)
A7: 2030 | B7: 40814669 | C7: 0.18 | D7: =B7*C7 | E7: =-Assumptions!B5*D7 | F7: =D7+E7 | G7: =F7 - (Assumptions!B7*B7) - (Assumptions!B6*B7) - (Assumptions!B8*B7)
A9: PV of FCF | G9: =NPV(Assumptions!B3, G3:G7)
A10: Terminal Value | G10: =G7*(1+Assumptions!B4)/(Assumptions!B3-Assumptions!B4)
A11: PV Terminal | G11: =G10/(1+Assumptions!B3)^5
A12: Enterprise Value | G12: =G9+G11

Sheet ROI_Case
A1: ROI Decision Memo (Example: Marketplace Ads Expansion)
A2: Item | B2: Value | C2: Unit | D2: Notes
A3: Upfront investment | B3: 2500000 | C3: $ | D3: One-time build + launch
A4: Annual incremental revenue | B4: 4200000 | C4: $ | D4: Expected lift from new ad placements
A5: Incremental gross margin % | B5: 0.65 | C5: % | D5: Contribution after traffic costs
A6: Annual opex | B6: 900000 | C6: $ | D6: Ad ops + support
A7: Project life | B7: 4 | C7: Years | D7: Conservative evaluation horizon
A8: Discount rate | B8: 0.1 | C8: % | D8: Use WACC for NPV
A10: Outputs
A11: Annual cash flow | B11: =B4*B5-B6
A12: Payback (years) | B12: =B3/B11
A13: NPV | B13: =NPV(B8, B11,B11,B11,B11) - B3
A14: IRR | B14: =IRR({-B3,B11,B11,B11,B11})
