Workbook

Sheet Scenario Inputs
A1: Amazon Marketplace Analytics — Forecast Model (Driver-Based + Scenarios)
A2: Pick a scenario and edit assumptions. Output sheet updates automatically.
A4: Scenario | B4: Base
A6: Driver | B6: Base | C6: Bull | D6: Bear | E6: Driver | F6: Active Assumption
A7: Revenue Growth | B7: 0.1 | C7: 0.18 | D7: 0.05 | E7: =A7 | F7: =INDEX(B7:D7,1,MATCH($B$4,$B$6:$D$6,0))
A8: COGS % of Revenue | B8: 0.45 | C8: 0.42 | D8: 0.48 | E8: =A8 | F8: =INDEX(B8:D8,1,MATCH($B$4,$B$6:$D$6,0))
A9: Opex Growth | B9: 0.06 | C9: 0.08 | D9: 0.04 | E9: =A9 | F9: =INDEX(B9:D9,1,MATCH($B$4,$B$6:$D$6,0))
A10: Tax Rate | B10: 0.24 | C10: 0.22 | D10: 0.26 | E10: =A10 | F10: =INDEX(B10:D10,1,MATCH($B$4,$B$6:$D$6,0))

Sheet Forecast Output
A1: 3-Year Forecast Summary
A2: Edit starting values below. Forecast uses scenario drivers from Scenario Inputs.
A4: Line Item | B4: Year 0 (Actual) | C4: Year 1 | D4: Year 2 | E4: Year 3 | F4: Notes
A5: Revenue | B5: 1200000 | C5: =B5*(1+'Scenario Inputs'!$F$7) | D5: =C5*(1+'Scenario Inputs'!$F$7) | E5: =D5*(1+'Scenario Inputs'!$F$7)
A6: COGS | B6: =B5*'Scenario Inputs'!F8 | C6: =C5*'Scenario Inputs'!$F$8 | D6: =D5*'Scenario Inputs'!$F$8 | E6: =E5*'Scenario Inputs'!$F$8
A7: Gross Profit | B7: =B5-B6 | C7: =C5-C6 | D7: =D5-D6 | E7: =E5-E6
A8: Operating Expenses | B8: 450000 | C8: =B8*(1+'Scenario Inputs'!$F$9) | D8: =C8*(1+'Scenario Inputs'!$F$9) | E8: =D8*(1+'Scenario Inputs'!$F$9)
A9: Operating Income | B9: =B7-B8 | C9: =C7-C8 | D9: =D7-D8 | E9: =E7-E8
A10: Taxes | B10: =MAX(0,B9)*'Scenario Inputs'!F10 | C10: =MAX(0,C9)*'Scenario Inputs'!$F$10 | D10: =MAX(0,D9)*'Scenario Inputs'!$F$10 | E10: =MAX(0,E9)*'Scenario Inputs'!$F$10
A11: Net Income | B11: =B9-B10 | C11: =C9-C10 | D11: =D9-D10 | E11: =E9-E10

Sheet FA_Workstreams
A1: Financial Analyst Workstreams — 02 Amazon Marketplace Analytics
A2: This sheet summarizes how the Excel models + SQL + Python artifacts in this project map to core Financial Analyst responsibilities.
A4: Workstream | B4: What you do | C4: Key metrics | D4: Tools used | E4: Deliverables
A5: Budgeting & Forecasting | B5: Develop annual budgets and rolling forecasts using driver-based assumptions and scenario modeling. | C5: Revenue, Gross Margin, OpEx, EBITDA, Net Income, Cash Flow, Budget vs Actual (BvA) variances | D5: Excel (Budget vs Actual + Forecast + Scenario Toggle), Power BI/Tableau dashboards | E5: Annual budget workbook, 12-month rolling forecast, best/base/worst scenario summary
A6: Financial Analysis | B6: Analyze performance, identify trends, explain variances, and assess profitability at product/department level. | C6: MoM/QoQ/YoY growth, variance % and $ impact, contribution margin, ROA/ROIC, unit economics | D6: SQL (joins, KPI tables), Excel (variance bridge), Python (trend charts) | E6: Variance bridge, profitability by segment, trend commentary + recommendation bullets
A7: Strategic Planning | B7: Support long-term goals, capital allocation, and evaluate new investments/projects with ROI logic. | C7: NPV, IRR, Payback Period, CAC:LTV, portfolio mix, capacity/utilization | D7: Excel (DCF/NPV models), SQL (cohorts/segments), dashboards for exec review | E7: Investment memo inputs, capital allocation scenario, go/no-go recommendation
A8: Business Partnering | B8: Collaborate with Sales/Marketing/R&D/Ops to understand financial impacts and drive operational improvements. | C8: Pipeline-to-revenue, price/volume/mix, campaign ROI, churn/retention impact, cost-to-serve | D8: Stakeholder intake template, KPI scorecard, scenario toggle for tradeoffs | E8: Cross-functional KPI scorecard, action plan with owners/dates, impact estimate
A9: Reporting | B9: Create clear reports and presentations for senior management/board with consistent definitions and story. | C9: Executive KPIs, variance callouts, forecast accuracy, risk/opportunity pipeline | D9: PowerPoint-ready exports, dashboard screenshots, narrative summary in Excel | E9: Monthly performance pack, board-ready highlights, one-page exec summary
A11: How to use: Keep this tab in your GitHub Excel artifacts. When presenting your project, reference this sheet to explain how your models support budgeting, forecasting, strategic decisions, and executive reporting.

Sheet Executive_Reporting_Pack
A1: Executive Reporting Pack
A3: KPI Snapshot
A4: • Revenue Growth (YoY): 14.8%
A5: • Gross Margin: 62.4%
A6: • Operating Margin: 28.1%
A7: • Customer Acquisition Cost: $42
A8: • LTV:CAC Ratio: 5.6x
A10: Key Highlights
A11: • Strong revenue acceleration driven by enterprise customer expansion.
A12: • Marketing efficiency improved with CAC down 11% quarter-over-quarter.
A13: • High-margin product mix shift contributed to margin expansion.
A15: Risks & Watchouts
... A22: • Update pricing experiments for underperforming plans.
